pgf_formatter/__about__.py
pgf_formatter/__init__.py
pgf_formatter/formatter.py
pgf_formatter-0.2.0.dist-info/METADATA
pgf_formatter-0.2.0.dist-info/WHEEL
pgf_formatter-0.2.0.dist-info/licenses/LICENSE.txt
pgf_formatter-0.2.0.dist-info/RECORD
