Metadata-Version: 2.1
Name: pgf-formatter
Version: 0.2.0
Summary: Embedding PDF images in Jupyter notebooks
Project-URL: Documentation, https://github.com/daizutabi/pgf-formatter#readme
Project-URL: Issues, https://github.com/daizutabi/pgf-formatter/issues
Project-URL: Source, https://github.com/daizutabi/pgf-formatter
Author-email: daizutabi <daizutabi@gmail.com>
License-Expression: MIT
License-File: LICENSE.txt
Classifier: Development Status :: 4 - Beta
Classifier: Programming Language :: Python
Classifier: Programming Language :: Python :: 3.8
Classifier: Programming Language :: Python :: 3.9
Classifier: Programming Language :: Python :: 3.10
Classifier: Programming Language :: Python :: 3.11
Classifier: Programming Language :: Python :: 3.12
Classifier: Programming Language :: Python :: Implementation :: CPython
Classifier: Programming Language :: Python :: Implementation :: PyPy
Requires-Python: >=3.8
Requires-Dist: ipython
Requires-Dist: matplotlib
